[
  {
    "id": 1,
    "title": "Attack on Titan",
    "description": "Em um mundo onde a humanidade vive dentro de cidades cercadas por três enormes muralhas que os protegem dos gigantescos humanóides devoradores de humanos chamados de Titãs.",
    "thumbnail": "https://raw.githubusercontent.com/jonarasgames/AniVerse/refs/heads/main/images/thumbnails/attack.png",
    "trailer": "https://www.youtube.com/embed/MGRm4IzK1SQ?autoplay=1&mute=1&enablejsapi=1",
    "type": "anime",
    "dateAdded": "2023-10-20",
    "categories": [
      "action",
      "drama",
      "fantasy"
    ],
    "seasons": [
      {
        "number": 1,
        "episodes": [
          {
            "title": "Ao Grito de 'Você Está Livre'",
            "videoUrl": "https://store3.gofile.io/download/web/2249da05-3798-46e8-958e-f71a8c4957f9/Avatar%20IV%20Video.mp4",
            "duration": 1440
          },
          {
            "title": "Aquele Dia",
            "videoUrl": "https://example.com/attack-on-titan-s1e2.mp4",
            "duration": 1440
          }
        ]
      },
      {
        "number": 2,
        "episodes": [
          {
            "title": "A Muralha Sina",
            "videoUrl": "https://example.com/attack-on-titan-s2e1.mp4",
            "duration": 1440
          }
        ]
      }
    ],
    "year": 2013,
    "rating": 4.8,
    "openings": [
      {
        "title": "Guren no Yumiya",
        "artist": "Linked Horizon",
        "audio": "https://example.com/attack-op1.mp3",
        "cover": "https://example.com/attack-op1-cover.jpg",
        "type": "opening",
        "season": 1
      },
      {
        "title": "Shinzo wo Sasageyo!",
        "artist": "Linked Horizon",
        "audio": "https://example.com/attack-op2.mp3",
        "cover": "https://example.com/attack-op2-cover.jpg",
        "type": "opening",
        "season": 2
      }
    ],
    "endings": [
      {
        "title": "Utsukushiki Zankoku na Sekai",
        "artist": "Yoko Hikasa",
        "audio": "https://example.com/attack-ed1.mp3",
        "cover": "https://example.com/attack-ed1-cover.jpg",
        "type": "ending",
        "season": 1
      }
    ],
    "osts": {
      "Attack on Titan Original Soundtrack": {
        "year": 2013,
        "cover": "https://example.com/attack-ost1-cover.jpg",
        "tracks": [
          {
            "title": "ətˈæk 0N tάɪtn",
            "artist": "Hiroyuki Sawano",
            "audio": "https://example.com/attack-ost1.mp3",
            "duration": 245
          },
          {
            "title": "Vogel im Käfig",
            "artist": "Hiroyuki Sawano",
            "audio": "https://example.com/attack-ost2.mp3",
            "duration": 328
          }
        ]
      },
      "Attack on Titan Season 2 OST": {
        "year": 2017,
        "cover": "https://example.com/attack-ost2-cover.jpg",
        "tracks": [
          {
            "title": "Barricades",
            "artist": "Hiroyuki Sawano",
            "audio": "https://example.com/attack-ost3.mp3",
            "duration": 215
          }
        ]
      }
    }
  },
  {
    "id": 2,
    "title": "Demon Slayer: Mugen Train",
    "description": "Tanjiro e seus amigos embarcam no Trem Infinito para ajudar o Pilar das Chamas, Kyojuro Rengoku, a combater um demônio que tem atormentado os passageiros.",
    "thumbnail": "https://raw.githubusercontent.com/jonarasgames/AniVerse/refs/heads/main/images/thumbnails/demonmovie.png",
    "trailer": "https://www.youtube.com/embed/ATJYac_dORw?autoplay=1&mute=1&enablejsapi=1",
    "type": "movie",
    "dateAdded": "2023-10-19",
    "categories": [
      "action",
      "fantasy"
    ],
    "seasons": [
      {
        "number": 1,
        "episodes": [
          {
            "title": "Demon Slayer: Mugen Train",
            "videoUrl": "https://example.com/demon-slayer-movie.mp4",
            "duration": 6600
          }
        ]
      }
    ],
    "year": 2020,
    "rating": 4.9,
    "openings": [
      {
        "title": "Homura",
        "artist": "LiSA",
        "audio": "https://example.com/demon-movie-op1.mp3",
        "cover": "https://example.com/demon-movie-op1-cover.jpg",
        "type": "opening",
        "season": 1
      }
    ],
    "endings": [
      {
        "title": "Kamado Tanjiro no Uta",
        "artist": "Go Shiina",
        "audio": "https://example.com/demon-movie-ed1.mp3",
        "cover": "https://example.com/demon-movie-ed1-cover.jpg",
        "type": "ending",
        "season": 1
      }
    ],
    "osts": {
      "Demon Slayer: Mugen Train Original Soundtrack": {
        "year": 2020,
        "cover": "https://example.com/demon-movie-ost1-cover.jpg",
        "tracks": [
          {
            "title": "Rengoku's Theme",
            "artist": "Yuki Kajiura, Go Shiina",
            "audio": "https://example.com/demon-movie-ost1.mp3",
            "duration": 245
          }
        ]
      }
    }
  },
  {
    "id": 3,
    "title": "Jujutsu Kaisen 0",
    "description": "Yuta Okkotsu ganha o controle de um espírito amaldiçoado extremamente poderoso e se matricula na Tokyo Prefectural Jujutsu High School sob a orientação de Satoru Gojo.",
    "thumbnail": "https://raw.githubusercontent.com/jonarasgames/AniVerse/refs/heads/main/images/thumbnails/jujutsumovie.png",
    "trailer": "https://www.youtube.com/embed/2docezZl574?autoplay=1&mute=1&enablejsapi=1",
    "type": "movie",
    "dateAdded": "2023-10-18",
    "categories": [
      "action",
      "supernatural"
    ],
    "seasons": [
      {
        "number": 1,
        "episodes": [
          {
            "title": "Jujutsu Kaisen 0",
            "videoUrl": "https://example.com/jujutsu-kaisen-0.mp4",
            "duration": 6300
          }
        ]
      }
    ],
    "year": 2021,
    "rating": 4.7,
    "openings": [
      {
        "title": "Ichizu",
        "artist": "King Gnu",
        "audio": "https://example.com/jujutsu0-op1.mp3",
        "cover": "https://example.com/jujutsu0-op1-cover.jpg",
        "type": "opening",
        "season": 1
      }
    ],
    "endings": [
      {
        "title": "Sakayume",
        "artist": "King Gnu",
        "audio": "https://example.com/jujutsu0-ed1.mp3",
        "cover": "https://example.com/jujutsu0-ed1-cover.jpg",
        "type": "ending",
        "season": 1
      }
    ],
    "osts": {
      "Jujutsu Kaisen 0 Original Soundtrack": {
        "year": 2021,
        "cover": "https://example.com/jujutsu0-ost1-cover.jpg",
        "tracks": [
          {
            "title": "Yuta Okkotsu's Theme",
            "artist": "Hiroaki Tsutsumi",
            "audio": "https://example.com/jujutsu0-ost1.mp3",
            "duration": 210
          }
        ]
      }
    }
  },
  {
    "id": 4,
    "title": "One Piece: Stampede",
    "description": "Piratas de todo o mundo se reúnem para o Pirate Expo, organizado pelo misterioso Buena Festa, onde o tesouro deixado pelo lendário Gol D. Roger está em jogo.",
    "thumbnail": "https://raw.githubusercontent.com/jonarasgames/AniVerse/refs/heads/main/images/thumbnails/onepiecemovie.png",
    "trailer": "https://www.youtube.com/embed/CZzQ6dJkik0?autoplay=1&mute=1&enablejsapi=1",
    "type": "movie",
    "dateAdded": "2023-10-17",
    "categories": [
      "action",
      "adventure"
    ],
    "seasons": [
      {
        "number": 1,
        "episodes": [
          {
            "title": "One Piece: Stampede",
            "videoUrl": "https://example.com/one-piece-stampede.mp4",
            "duration": 6300
          }
        ]
      }
    ],
    "year": 2019,
    "rating": 4.6,
    "openings": [
      {
        "title": "GONG",
        "artist": "WANIMA",
        "audio": "https://example.com/op-stampede-op1.mp3",
        "cover": "https://example.com/op-stampede-op1-cover.jpg",
        "type": "opening",
        "season": 1
      }
    ],
    "endings": [
      {
        "title": "Memories",
        "artist": "Maki Otsuki",
        "audio": "https://example.com/op-stampede-ed1.mp3",
        "cover": "https://example.com/op-stampede-ed1-cover.jpg",
        "type": "ending",
        "season": 1
      }
    ],
    "osts": {
      "One Piece: Stampede Original Soundtrack": {
        "year": 2019,
        "cover": "https://example.com/op-stampede-ost1-cover.jpg",
        "tracks": [
          {
            "title": "Stampede Theme",
            "artist": "Kohei Tanaka",
            "audio": "https://example.com/op-stampede-ost1.mp3",
            "duration": 245
          }
        ]
      }
    }
  },
  {
    "id": 5,
    "title": "My Hero Academia: Heroes Rising",
    "description": "Os alunos da Classe 1-A visitam a Ilha Nabu, onde eventualmente acabam enfrentando um vilão com uma peculiaridade alarmante.",
    "thumbnail": "https://raw.githubusercontent.com/jonarasgames/AniVerse/refs/heads/main/images/thumbnails/mhamovie.png",
    "trailer": "https://www.youtube.com/embed/VQGCKyvzIM4?autoplay=1&mute=1&enablejsapi=1",
    "type": "movie",
    "dateAdded": "2023-10-16",
    "categories": [
      "action",
      "superhero"
    ],
    "seasons": [
      {
        "number": 1,
        "episodes": [
          {
            "title": "My Hero Academia: Heroes Rising",
            "videoUrl": "https://example.com/mha-heroes-rising.mp4",
            "duration": 6240
          }
        ]
      }
    ],
    "year": 2019,
    "rating": 4.8,
    "openings": [
      {
        "title": "Higher Ground",
        "artist": "Survive Said The Prophet",
        "audio": "https://example.com/mha-movie-op1.mp3",
        "cover": "https://example.com/mha-movie-op1-cover.jpg",
        "type": "opening",
        "season": 1
      }
    ],
    "endings": [
      {
        "title": "Dakara, Hitori ja nai",
        "artist": "Little Glee Monster",
        "audio": "https://example.com/mha-movie-ed1.mp3",
        "cover": "https://example.com/mha-movie-ed1-cover.jpg",
        "type": "ending",
        "season": 1
      }
    ],
    "osts": {
      "My Hero Academia: Heroes Rising Original Soundtrack": {
        "year": 2019,
        "cover": "https://example.com/mha-movie-ost1-cover.jpg",
        "tracks": [
          {
            "title": "Heroes Rising Theme",
            "artist": "Yuki Hayashi",
            "audio": "https://example.com/mha-movie-ost1.mp3",
            "duration": 245
          }
        ]
      }
    }
  },
  {
    "id": 6,
    "title": "Neon Genesis Evangelion: The End of Evangelion",
    "description": "A SEELE ordena um ataque à NERV para destruir os EVAs antes que Gendo consiga provocar o terceiro impacto e a união das almas humanas.",
    "thumbnail": "https://raw.githubusercontent.com/jonarasgames/AniVerse/refs/heads/main/images/thumbnails/evangelionmovie.png",
    "trailer": "https://geo.dailymotion.com/player.html?video=x24kdhz",
    "type": "movie",
    "dateAdded": "2023-10-15",
    "categories": [
      "drama",
      "mecha",
      "psychological"
    ],
    "seasons": [
      {
        "number": 1,
        "episodes": [
          {
            "title": "The End of Evangelion",
            "videoUrl": "https://seed306.bitchute.com/8xBkY2iNMQ05/9ePjcp185z3J.mp4",
            "duration": 5222
          }
        ]
      }
    ],
    "year": 1997,
    "rating": 8.1,
    "openings": [
      {
        "title": "A Cruel Angel's Thesis",
        "artist": "Yoko Takahashi",
        "audio": "https://example.com/eva-op1.mp3",
        "cover": "https://example.com/eva-op1-cover.jpg",
        "type": "opening",
        "season": 1
      }
    ],
    "endings": [
      {
        "title": "Fly Me to the Moon",
        "artist": "Claire",
        "audio": "https://example.com/eva-ed1.mp3",
        "cover": "https://example.com/eva-ed1-cover.jpg",
        "type": "ending",
        "season": 1
      }
    ],
    "osts": {
      "The End of Evangelion Original Soundtrack": {
        "year": 1997,
        "cover": "https://example.com/eva-movie-ost1-cover.jpg",
        "tracks": [
          {
            "title": "Komm, süsser Tod",
            "artist": "Arianne",
            "audio": "https://example.com/eva-movie-ost1.mp3",
            "duration": 245
          }
        ]
      }
    }
  },
  {
    "id": 7,
    "title": "Azumanga Daioh",
    "description": "Uma série animada cômica e altamente imprevisível que acompanha um grupo de meninas do ensino médio e seus professores.",
    "thumbnail": "https://raw.githubusercontent.com/jonarasgames/AniVerse/refs/heads/main/images/thumbnails/azudaioh.png",
    "trailer": "https://www.youtube.com/embed/mqqxHv-BBSY?autoplay=1&mute=1&enablejsapi=1",
    "type": "anime",
    "dateAdded": "2025-07-28",
    "categories": [
      "comedy",
      "slice of life"
    ],
    "seasons": [
      {
        "number": 1,
        "episodes": [
          {
            "title": "A Diante, os Exames de Entrada!",
            "videoUrl": "https://files.catbox.moe/9sqmzv.mp4",
            "duration": 1447
          },
          {
            "title": "Dia da Osaka",
            "videoUrl": "https://files.catbox.moe/tff74x.mp4",
            "duration": 1447
          },
          {
            "title": "Nyamo",
            "videoUrl": "https://files.catbox.moe/i1qpqg.mp4",
            "duration": 1447
          },
          {
            "title": "Piscina! Piscina! Piscina!",
            "videoUrl": "https://files.catbox.moe/0cadkg.mp4",
            "duration": 1447
          },
          {
            "title": "Férias de verão",
            "videoUrl": "https://files.catbox.moe/kevo22.mp4",
            "duration": 1447
          },
          {
            "title": "Festival de Esportes",
            "videoUrl": "https://files.catbox.moe/mzs9xm.mp4",
            "duration": 1447
          },
          {
            "title": "Festival Cultural",
            "videoUrl": "https://files.catbox.moe/m7wj5i.mp4",
            "duration": 1447
          },
          {
            "title": "Especial Sonhos de Ano Novo",
            "videoUrl": "https://files.catbox.moe/uztzgt.mp4",
            "duration": 1447
          },
          {
            "title": "Sakaki-san",
            "videoUrl": "https://files.catbox.moe/uvvlf1.mp4",
            "duration": 1447
          },
          {
            "title": "Nós Somos Estudantes do Segundo Ano!",
            "videoUrl": "https://files.catbox.moe/ftmfgn.mp4",
            "duration": 1447
          },
          {
            "title": "Kagura e Sakaki",
            "videoUrl": "https://files.catbox.moe/9jmrp0.mp4",
            "duration": 1447
          },
          {
            "title": "Dia da Chyio-chan",
            "videoUrl": "https://files.catbox.moe/s0fowe.mp4",
            "duration": 1447
          },
          {
            "title": "Provas",
            "videoUrl": "https://files.catbox.moe/xytmny.mp4",
            "duration": 1447
          },
          {
            "title": "O Mar, Quimonos e Festa",
            "videoUrl": "https://files.catbox.moe/fug66z.mp4",
            "duration": 1447
          },
          {
            "title": "Festival de Esportes do Segundo Ano",
            "videoUrl": "https://files.catbox.moe/ljm0y8.mp4",
            "duration": 1447
          },
          {
            "title": "Festival Cultural do Segundo Ano",
            "videoUrl": "https://files.catbox.moe/1hqjb2.mp4",
            "duration": 1447
          },
          {
            "title": "Fim do Segundo Semestre e Natal",
            "videoUrl": "https://files.catbox.moe/ttnid0.mp4",
            "duration": 1447
          },
          {
            "title": "Provações da Koyomi",
            "videoUrl": "https://files.catbox.moe/paca5b.mp4",
            "duration": 1447
          },
          {
            "title": "Uma Noite de Primavera",
            "videoUrl": "https://files.catbox.moe/ngk2ns.mp4",
            "duration": 1447
          },
          {
            "title": "Terceiro Ano",
            "videoUrl": "https://files.catbox.moe/s6uxsy.mp4",
            "duration": 1447
          },
          {
            "title": "Excursão Escolar",
            "videoUrl": "https://files.catbox.moe/he35zp.mp4",
            "duration": 1447
          },
          {
            "title": "Estudos Para os Exames de Admissão",
            "videoUrl": "https://files.catbox.moe/xn1deg.mp4",
            "duration": 1447
          },
          {
            "title": "Último Festival de Esportes",
            "videoUrl": "https://files.catbox.moe/h6dfvx.mp4",
            "duration": 1447
          },
          {
            "title": "Yamamayaa",
            "videoUrl": "https://files.catbox.moe/moqg4k.mp4",
            "duration": 1447
          },
          {
            "title": "Em Frente: Os Exames de Admissão!",
            "videoUrl": "https://files.catbox.moe/58664b.mp4",
            "duration": 1447
          },
          {
            "title": "Cerimônia de Formatura",
            "videoUrl": "https://files.catbox.moe/xg8jlr.mp4",
            "duration": 1447
          }
        ]
      }
    ],
    "year": 2002,
    "rating": 8.1,
    "openings": [
      {
        "title": "Soramimi Cake",
        "artist": "Oranges & Lemons",
        "audio": "https://kappa.vgmsite.com/soundtracks/azumanga-daiou-the-animation-utaimasho/eyugksoc/01.%20Ear-Playing-Tricks%20Cake.mp3",
        "cover": "https://static.wikia.nocookie.net/azumanga/images/8/80/Soramimi_Cake_Raspberry_heaven.jpg",
        "type": "opening",
        "season": 1
      }
    ],
    "endings": [
      {
        "title": "Raspberry Heaven",
        "artist": "Oranges & Lemons",
        "audio": "https://kappa.vgmsite.com/soundtracks/azumanga-daiou-the-animation-utaimasho/ieokccdk/12.%20raspberry%20heaven.mp3",
        "cover": "https://static.wikia.nocookie.net/azumanga/images/8/80/Soramimi_Cake_Raspberry_heaven.jpg",
        "type": "ending",
        "season": 1
      }
    ],
    "osts": {
      "Azumanga Daioh Original Soundtrack": {
        "title": "Azumanga Daioh Original Soundtrack",
        "year": 2002,
        "cover": "https://raw.githubusercontent.com/jonarasgames/AniVerse/refs/heads/main/images/thumbnails/ranmanet.png",
        "tracks": [
          {
            "title": "Azumanga Daioh Main Theme",
            "artist": "Masaki Kurihara",
            "audio": "https://example.com/azumanga-ost1.mp3",
            "duration": 120
          }
        ]
      }
    }
  },
  {
    "id": 8,
    "title": "Ranma 1/2",
    "description": "As aventuras românticas e as desventuras de um jovem que é atingido por uma maldição que o faz mudar de gênero.",
    "thumbnail": "https://raw.githubusercontent.com/jonarasgames/AniVerse/refs/heads/main/images/thumbnails/ranmanet.png",
    "trailer": "https://www.youtube.com/watch?v=V77a7NUof4I",
    "type": "anime",
    "dateAdded": "2025-06-29",
    "categories": [
      "adventure",
      "comedy",
      "romance"
    ],
    "seasons": [
      {
        "number": 1,
        "episodes": [
          {
            "title": "Episódio 1",
            "videoUrl": "https://zggg98sgwbg1gh.bitchute.com/8xBkY2iNMQ05/7E6G46cLvHzw.mp4",
            "duration": 1462
          },
          {
            "title": "Episódio 2",
            "videoUrl": "https://seed125.bitchute.com/8xBkY2iNMQ05/5vPVHLKrOKcG.mp4",
            "duration": 1462
          },
          {
            "title": "Episódio 3",
            "videoUrl": "https://files.catbox.moe/cubuaj.mp4",
            "duration": 1462
          },
          {
            "title": "Episódio 4",
            "videoUrl": "https://seed306.bitchute.com/8xBkY2iNMQ05/iEzqxVQFpoeA.mp4",
            "duration": 1466
          },
          {
            "title": "Episódio 5",
            "videoUrl": "https://files.catbox.moe/w4dzm7.mp4",
            "duration": 1470
          },
          {
            "title": "Episódio 6",
            "videoUrl": "https://seed128.bitchute.com/8xBkY2iNMQ05/r0FTV3eZulwC.mp4",
            "duration": 1462
          },
          {
            "title": "Episódio 7",
            "videoUrl": "https://seed307.bitchute.com/8xBkY2iNMQ05/1AWqmaf9YRM7.mp4",
            "duration": 1468
          },
          {
            "title": "Episódio 8",
            "videoUrl": "https://zggg98sgwbg1gh.bitchute.com/8xBkY2iNMQ05/7UFXTWu9Yi7X.mp4",
            "duration": 1472
          },
          {
            "title": "Episódio 9",
            "videoUrl": "https://files.catbox.moe/8agufk.mp4",
            "duration": 1466
          },
          {
            "title": "Episódio 10",
            "videoUrl": "https://seed306.bitchute.com/8xBkY2iNMQ05/Af9TpTaQkFJW.mp4",
            "duration": 1381
          },
          {
            "title": "Episódio 11",
            "videoUrl": "https://seed163.bitchute.com/8xBkY2iNMQ05/0VlRkpy48hJJ.mp4",
            "duration": 1466
          },
          {
            "title": "Episódio 12",
            "videoUrl": "https://files.catbox.moe/9wfwe9.mp4",
            "duration": 1466
          }
        ]
      }
    ],
    "year": 2024,
    "rating": 7.9,
    "openings": [
      {
        "title": "Iinazukekkyun",
        "artist": " Ano",
        "audio": "https://files.catbox.moe/1qjte8.mp3",
        "cover": "https://m.media-amazon.com/images/I/81MCmZcJcOL._UF1000,1000_QL80_.jpg",
        "type": "opening",
        "season": 1
      }
    ],
    "endings": [
      {
        "title": "Anta Nante",
        "artist": "Riria",
        "audio": "https://files.catbox.moe/09fe5t.mp3",
        "cover": "https://i.scdn.co/image/ab67616d0000b27374b94a678dffddb3abca4f97",
        "type": "ending",
        "season": 1
      }
    ],
    "osts": {
      "Ranma 1/2 2024 Original Soundtrack": {
        "year": 2024,
        "cover": "https://example.com/ranma2024-ost1-cover.jpg",
        "tracks": [
          {
            "title": "Ranma 1/2 2024 Main Theme",
            "artist": "Composer Name",
            "audio": "https://example.com/ranma2024-ost1.mp3",
            "duration": 180
          }
        ]
      }
    }
  },
  {
    "id": 9,
    "title": "Komi Can't Communicate",
    "description": "Uma aluna de elite e distante é de facto muito retraída e ansiosa por comunicar com os outros. Um estudante comum faz amizade com ela e ajuda-a a abrir-se e a falar com as pessoas.",
    "thumbnail": "https://raw.githubusercontent.com/jonarasgames/AniVerse/refs/heads/main/images/thumbnails/komi.png",
    "trailer": "https://www.youtube.com/watch?v=erF7lSzkTYA&pp=0gcJCdgAo7VqN5tD",
    "type": "anime",
    "dateAdded": "2025-06-29",
    "categories": [
      "comedy",
      "slice of life"
    ],
    "seasons": [
      {
        "number": 1,
        "episodes": [
          {
            "title": "É só que eu queria poder falar.",
            "videoUrl": "https://files.catbox.moe/adc3gu.mp4",
            "duration": 1496
          },
          {
            "title": "É só uma uma amizade de infância e mais.",
            "videoUrl": "https://files.catbox.moe/3bb5he.mp4",
            "duration": 1496
          },
          {
            "title": "É só medo e mais.",
            "videoUrl": "https://files.catbox.moe/rwvwkv.mp4",
            "duration": 1498
          },
          {
            "title": "É só uma questão física e mais.",
            "videoUrl": "https://files.catbox.moe/2pnhw4.mp4",
            "duration": 1496
          },
          {
            "title": "É só meu uniforme de verão e mais.",
            "videoUrl": "https://files.catbox.moe/fnpqqv.mp4",
            "duration": 1498
          },
          {
            "title": "É só uma brincadeira e mais.",
            "videoUrl": "https://files.catbox.moe/i3b90m.mp4",
            "duration": 1496
          },
          {
            "title": "É só a piscina e mais.",
            "videoUrl": "https://files.catbox.moe/bn8qlh.mp4",
            "duration": 1496
          },
          {
            "title": "É só Obom e mais.",
            "videoUrl": "https://files.catbox.moe/fsvlbl.mp4",
            "duration": 1496
          },
          {
            "title": "É só uma criança do interior e mais.",
            "videoUrl": "https://files.catbox.moe/pma44d.mp4",
            "duration": 1496
          },
          {
            "title": "É só dia de esporte e mais.",
            "videoUrl": "https://files.catbox.moe/enmpd4.mp4",
            "duration": 1500
          },
          {
            "title": "São propostas para o festival e mais.",
            "videoUrl": "https://files.catbox.moe/s5h76e.mp4",
            "duration": 1508
          },
          {
            "title": "É só o festival cultural.",
            "videoUrl": "https://files.catbox.moe/tnzjbb.mp4",
            "duration": 1494
          }
        ]
      },
      {
        "number": 2,
        "episodes": [
          {
            "title": "É só a chegada do inverno. E mais.",
            "videoUrl": "https://rr1---sn-8v5oxucg-nn5e.googlevideo.com/videoplayback?expire=1751272359&ei=J9thaNXbKLjy3rsPqazDkAI&ip=200.106.211.8&id=0ae645603ab00bc0&itag=22&source=blogger&xpc=Egho7Zf3LnoBAQ%3D%3D&met=1751243559,&mh=sg&mm=31&mn=sn-8v5oxucg-nn5e&ms=au&mv=m&mvi=1&pl=24&rms=au,au&susc=bl&eaua=OfoyTv86HTM&mime=video/mp4&vprv=1&rqh=1&dur=1504.026&lmt=1663907493508175&mt=1751242871&txp=1311224&sparams=expire,ei,ip,id,itag,source,xpc,susc,eaua,mime,vprv,rqh,dur,lmt&sig=AJfQdSswRgIhAPUW8bpoNZ3dV5d0gF4ZVANJ3kysFQ9W94z0L9gmrVD_AiEA2vfqPVRZqixVMG5ElbYmL5SjQnymK_KeJrTzek-OYnE%3D&lsparams=met,mh,mm,mn,ms,mv,mvi,pl,rms&lsig=APaTxxMwRgIhAJoCogAGK1ZsppQig1E8QXRnGlvw_SQGMsvFGRGaPgSrAiEAqOIIBwfHSMKPS7LBSOfzq0pHxP-gkSwdipAE16Rn2h4%3D&cpn=iOJPd9tqxZDCTpo2&c=WEB_EMBEDDED_PLAYER&cver=1.20250624.21.00",
            "duration": 1503
          },
          {
            "title": "É só um tufão. E mais.",
            "videoUrl": "https://rr1---sn-8v5oxucg-nn5e.googlevideo.com/videoplayback?expire=1751272481&ei=odthaOPkCJ6WvPIPt96JkQI&ip=200.106.211.8&id=a815d22f53b181fe&itag=18&source=blogger&xpc=Egho7Zf3LnoBAQ%3D%3D&met=1751243681,&mh=pN&mm=31&mn=sn-8v5oxucg-nn5e&ms=au&mv=m&mvi=1&pl=24&rms=au,au&susc=bl&eaua=OfoyTv86HTM&mime=video/mp4&vprv=1&rqh=1&dur=1506.023&lmt=1663907527156553&mt=1751243353&txp=1311224&sparams=expire,ei,ip,id,itag,source,xpc,susc,eaua,mime,vprv,rqh,dur,lmt&sig=AJfQdSswRgIhAJiCnIMM6_dPk-BPf0X3c45PY9aPqlEZ6F0vkwAfCjUtAiEAp1035TDJ3gmqHYFwfyWbWUY1ZM1pgMj_1P-841Yr93M%3D&lsparams=met,mh,mm,mn,ms,mv,mvi,pl,rms&lsig=APaTxxMwRgIhALro0mfCeNfx0ubf4N-Ki2mpPeQHUSWstvB3sYpEOZwOAiEA1o014fvsVdun_Yaa8fBYiTKJuIQUUhKtOnujrsfYBgY%3D&cpn=P0dHDwRAITDJQ28X&c=WEB_EMBEDDED_PLAYER&cver=1.20250624.21.00",
            "duration": 1505
          },
          {
            "title": "É só um pensamento. E mais.",
            "videoUrl": "https://rr3---sn-8v5oxucg-nn5e.googlevideo.com/videoplayback?expire=1751272537&ei=2dthaMzUIJvHvPIPyf-B8Ac&ip=200.106.211.8&id=03c62f8477b3b3d9&itag=18&source=blogger&xpc=Egho7Zf3LnoBAQ%3D%3D&met=1751243737,&mh=nq&mm=31&mn=sn-8v5oxucg-nn5e&ms=au&mv=m&mvi=3&pl=24&rms=au,au&susc=bl&eaua=OfoyTv86HTM&mime=video/mp4&vprv=1&rqh=1&dur=1506.023&lmt=1663907801012704&mt=1751243353&txp=1311224&sparams=expire,ei,ip,id,itag,source,xpc,susc,eaua,mime,vprv,rqh,dur,lmt&sig=AJfQdSswRAIgU_5x06bu5vpGxxIiCUPe1U1f20UTtSVsgFSCAc5URegCIDOFaYARvY7fSoM5YI4hlqRVFokbCEdnXa1_hCiQoRzJ&lsparams=met,mh,mm,mn,ms,mv,mvi,pl,rms&lsig=APaTxxMwRQIgMJP3b0SKyDc31xmsJo2Sh5F6Fm52pv07AW9pqqL-oFECIQDh-fadNCALodsHlhNuRNU3dt9MIfyitoLcpE9f-R2tdw%3D%3D&cpn=HhLc1Q76AMEGLCa0&c=WEB_EMBEDDED_PLAYER&cver=1.20250624.21.00",
            "duration": 1505
          },
          {
            "title": "É só um Natal Feliz.",
            "videoUrl": "https://rr1---sn-8v5oxucg-nn5l.googlevideo.com/videoplayback?expire=1751272589&ei=DdxhaI7DLdj2zLUPsbPUwA0&ip=200.106.211.8&id=4a16cbdc115b7fb3&itag=18&source=blogger&xpc=Egho7Zf3LnoBAQ%3D%3D&met=1751243789,&mh=YA&mm=31&mn=sn-8v5oxucg-nn5l&ms=au&mv=m&mvi=1&pl=24&rms=au,au&susc=bl&eaua=OfoyTv86HTM&mime=video/mp4&vprv=1&rqh=1&dur=1506.023&lmt=1663907812800053&mt=1751243353&txp=1311224&sparams=expire,ei,ip,id,itag,source,xpc,susc,eaua,mime,vprv,rqh,dur,lmt&sig=AJfQdSswRAIgWR4tY8oKmxrVOmUv0ASkyvl2U171Rh2UXEW9pYwYjRQCIGFNuWSEn_ndM7i9ZA7Z7hTiiqk_I1Iq0mssDQwldPfF&lsparams=met,mh,mm,mn,ms,mv,mvi,pl,rms&lsig=APaTxxMwRgIhAIt_QS6zAdJ-6fjXrlhZS85Ym1xThQd10FDjR7peMI1kAiEAsXyJ-n9egMQ9CmuwjXI66xKIkkPmA76YPFndz_YhRIg%3D&cpn=3QpgbT0ZqS0r5A5I&c=WEB_EMBEDDED_PLAYER&cver=1.20250624.21.00",
            "duration": 1505
          },
          {
            "title": "É só um boneco de neve. E mais.",
            "videoUrl": "https://rr2---sn-8v5oxucg-nn5e.googlevideo.com/videoplayback?expire=1751272643&ei=Q9xhaKSPGZ3oj-8PkfPm-AE&ip=200.106.211.8&id=743aeb0702c35a58&itag=18&source=blogger&xpc=Egho7Zf3LnoBAQ%3D%3D&met=1751243843,&mh=p3&mm=31&mn=sn-8v5oxucg-nn5e&ms=au&mv=m&mvi=2&pl=24&rms=au,au&susc=bl&eaua=OfoyTv86HTM&mime=video/mp4&vprv=1&rqh=1&dur=1502.005&lmt=1663907602502549&mt=1751243353&txp=1311224&sparams=expire,ei,ip,id,itag,source,xpc,susc,eaua,mime,vprv,rqh,dur,lmt&sig=AJfQdSswRQIgahDKRvmAL2Jv4KmmtilpIpoQPdNoJydPgs1ihysziQgCIQD-eYsfwHG2t6FP-K2YHLCbuzbyFhETuUjlg8Ruis-gLQ%3D%3D&lsparams=met,mh,mm,mn,ms,mv,mvi,pl,rms&lsig=APaTxxMwRAIgVWeVnZSZps7uvrBcRs-BcMDE21nCqr8HqzlpNd5iijsCIA6iYOS31RZlBQio0MkZbqdUHxILBV2ZjyDsyQ_OXrf_&cpn=xmtqfr7x4jeLsqIb&c=WEB_EMBEDDED_PLAYER&cver=1.20250624.21.00",
            "duration": 1501
          },
          {
            "title": "É só o ano-novo da galera. E mais.",
            "videoUrl": "https://rr2---sn-8v5oxucg-nn5l.googlevideo.com/videoplayback?expire=1751272726&ei=ltxhaKb0G6SAvPIP_fKN2QE&ip=200.106.211.8&id=0ef96deb124f1a46&itag=18&source=blogger&xpc=Egho7Zf3LnoBAQ%3D%3D&met=1751243926,&mh=Om&mm=31&mn=sn-8v5oxucg-nn5l&ms=au&mv=m&mvi=2&pl=24&rms=au,au&susc=bl&eaua=OfoyTv86HTM&mime=video/mp4&vprv=1&rqh=1&dur=1497.083&lmt=1663907543741484&mt=1751243823&txp=1311224&sparams=expire,ei,ip,id,itag,source,xpc,susc,eaua,mime,vprv,rqh,dur,lmt&sig=AJfQdSswRAIgZAsdkGWjr5uMD65EPxKNIC-iz-3yyxiagWnVFnYxXMECIFxrK6KTstGNVl8fU51_PJz-YCx4ABkVfQNln1yZq7x1&lsparams=met,mh,mm,mn,ms,mv,mvi,pl,rms&lsig=APaTxxMwRQIgVSCkh1E8b_xUePUCv-vZ_l2cjD7alqz2JHjP-TV8skwCIQC_vwHWBWFLcpJDO5RUTC8vRKiiMvYThIeb88CnwspK_g%3D%3D&cpn=CLbPxQVxtZZXD_XZ&c=WEB_EMBEDDED_PLAYER&cver=1.20250624.21.00",
            "duration": 1497
          },
          {
            "title": "É só um mal-entendido. E mais.",
            "videoUrl": "https://rr2---sn-8v5oxucg-nn5e.googlevideo.com/videoplayback?expire=1751272797&ei=3dxhaPrHEOap0_wP57aVqA0&ip=200.106.211.8&id=df14eb7b756db514&itag=18&source=blogger&xpc=Egho7Zf3LnoBAQ%3D%3D&met=1751243997,&mh=X9&mm=31&mn=sn-8v5oxucg-nn5e&ms=au&mv=m&mvi=2&pl=24&rms=au,au&susc=bl&eaua=OfoyTv86HTM&mime=video/mp4&vprv=1&rqh=1&dur=1504.026&lmt=1663907624304580&mt=1751243823&txp=1311224&sparams=expire,ei,ip,id,itag,source,xpc,susc,eaua,mime,vprv,rqh,dur,lmt&sig=AJfQdSswRQIhANQcL_R7eGv9SVOzDWb8w36b5nnf-Cb72_uu87HbQu2qAiAehdyVCvFlx0afiM8E1-MxRii33XTVk9m9ReSm0xCbBQ%3D%3D&lsparams=met,mh,mm,mn,ms,mv,mvi,pl,rms&lsig=APaTxxMwRgIhANmODjyvo8W0jChXAAFONipuaJdMLro0CZ0lRAUfNT4OAiEAmKoxNyJB36whqc89fOaVULYA_6Ly0lnTiJ18_d9uMVg%3D&cpn=M5DTQ-PIakneJndp&c=WEB_EMBEDDED_PLAYER&cver=1.20250624.21.00",
            "duration": 1503
          },
          {
            "title": "É só a viagem escolar.",
            "videoUrl": "https://rr1---sn-8v5oxucg-nn5l.googlevideo.com/videoplayback?expire=1751273031&ei=x91haI6jC_zby_sP1fDEEQ&ip=200.106.211.8&id=c2a5066d05d4b17b&itag=18&source=blogger&xpc=Egho7Zf3LnoBAQ%3D%3D&met=1751244231,&mh=Rm&mm=31&mn=sn-8v5oxucg-nn5l&ms=au&mv=m&mvi=1&pl=24&rms=au,au&susc=bl&eaua=OfoyTv86HTM&mime=video/mp4&vprv=1&rqh=1&dur=1473.747&lmt=1663907679694351&mt=1751244064&txp=1311224&sparams=expire,ei,ip,id,itag,source,xpc,susc,eaua,mime,vprv,rqh,dur,lmt&sig=AJfQdSswRQIhAMUjJrR9xR_JsEMUShHbjqBEkoTZgjFT9-uobDHD5nmPAiALpAsScA9D7edNZFMqv3EWqsh6gx3iMjgHMoRogZkyYw%3D%3D&lsparams=met,mh,mm,mn,ms,mv,mvi,pl,rms&lsig=APaTxxMwRAIgfzgZBbTBHeh98WgztTceiilMWxraqJYNxLjBoOIMt30CIHD-ZRKLw1XbuTJtE3V7LpsahyKz8hmvwzMQYFhqdTje&cpn=UhMtpDr4omty68Iy&c=WEB_EMBEDDED_PLAYER&cver=1.20250624.21.00",
            "duration": 1473
          },
          {
            "title": "É só o segundo dia da viagem escolar.",
            "videoUrl": "https://rr2---sn-8v5oxucg-nn5l.googlevideo.com/videoplayback?expire=1751273391&ei=L99haKaEM56WvPIPt96JkQI&ip=200.106.211.8&id=13dd5bcb4d84fabd&itag=18&source=blogger&xpc=Egho7Zf3LnoBAQ%3D%3D&met=1751244591,&mh=SZ&mm=31&mn=sn-8v5oxucg-nn5l&ms=au&mv=m&mvi=2&pl=24&rms=au,au&susc=bl&eaua=OfoyTv86HTM&mime=video/mp4&vprv=1&rqh=1&dur=1498.035&lmt=1663907799441891&mt=1751244306&txp=1311224&sparams=expire,ei,ip,id,itag,source,xpc,susc,eaua,mime,vprv,rqh,dur,lmt&sig=AJfQdSswRQIgSVCxBgw4n3dDuthKd7LpfjN3YFr06-kL7GSLUbUSOasCIQCSZObUIzD1i94hm7Q_0bKV366zrGwvcKxbYN_R9P-VUA%3D%3D&lsparams=met,mh,mm,mn,ms,mv,mvi,pl,rms&lsig=APaTxxMwRgIhAMaH6i-H4jCOBLyvLJdHWIwoxlnnUQMHdcIlQoLBidvaAiEAghvjmBXddwriGWZlfjVpMhqML5HU1mZhATDEArlPDzs%3D&cpn=Pu9fRYpOSBYEeTdq&c=WEB_EMBEDDED_PLAYER&cver=1.20250624.21.00",
            "duration": 1497
          },
          {
            "title": "É só o Dia dos Namorados.",
            "videoUrl": "https://rr2---sn-8v5oxucg-nn5e.googlevideo.com/videoplayback?expire=1751273431&ei=V99haPSFGY2sy_sPgtWZoAQ&ip=200.106.211.8&id=706b6a0094ed1bb9&itag=18&source=blogger&xpc=Egho7Zf3LnoBAQ%3D%3D&met=1751244631,&mh=d7&mm=31&mn=sn-8v5oxucg-nn5e&ms=au&mv=m&mvi=2&pl=24&rms=au,au&susc=bl&eaua=OfoyTv86HTM&mime=video/mp4&vprv=1&rqh=1&dur=1502.005&lmt=1663908013915863&mt=1751244066&txp=1311224&sparams=expire,ei,ip,id,itag,source,xpc,susc,eaua,mime,vprv,rqh,dur,lmt&sig=AJfQdSswRQIgQ6UB2M9yB2kcIZgkWbSc0RKfBb0_nrcfMdM2OLdewJMCIQD8Fjrn-E5LPapNaMAto8oU2O8sQsIgoUhn0nfrS6pCMg%3D%3D&lsparams=met,mh,mm,mn,ms,mv,mvi,pl,rms&lsig=APaTxxMwRAIgQauEhiatujTK637j2vOMegsyUcJx5feRGyPaJ_8swGUCIBLSaC_qdRCcd-0DI7hkzq5i8JTRPoWxspAopAq2TaWd&cpn=UdTT8s9fP97ptmhu&c=WEB_EMBEDDED_PLAYER&cver=1.20250624.21.00",
            "duration": 1501
          },
          {
            "title": "É só uma meia desfiada. E mais.",
            "videoUrl": "https://rr1---sn-8v5oxucg-nn5l.googlevideo.com/videoplayback?expire=1751273496&ei=mN9haNKqKKCGy_sPv_7QeA&ip=200.106.211.8&id=fb7282a27038b352&itag=18&source=blogger&xpc=Egho7Zf3LnoBAQ%3D%3D&met=1751244696,&mh=Ib&mm=31&mn=sn-8v5oxucg-nn5l&ms=au&mv=m&mvi=1&pl=24&rms=au,au&susc=bl&eaua=OfoyTv86HTM&mime=video/mp4&vprv=1&rqh=1&dur=1504.026&lmt=1663907845110408&mt=1751244306&txp=1311224&sparams=expire,ei,ip,id,itag,source,xpc,susc,eaua,mime,vprv,rqh,dur,lmt&sig=AJfQdSswRAIgAkps6bzeQlBUO17vPtGg7UI70IYEZ9fUA9XbWBmNOLICIHNjeP7ZAUmyAt46qumpR0jd-3Fl8SatP1I6U-cGaIkq&lsparams=met,mh,mm,mn,ms,mv,mvi,pl,rms&lsig=APaTxxMwRgIhAMnIX0jtqKhKbRLXItf6rISpPOnkpGd6EQiRWNXZaK8QAiEA148HOIdaQ91R4jmUN7_Fs4zGseJYJq4T9Uo_bzA5yDQ%3D&cpn=wCnwjiHMa3cH3whM&c=WEB_EMBEDDED_PLAYER&cver=1.20250624.21.00",
            "duration": 1503
          },
          {
            "title": "É só o White Day. E mais.",
            "videoUrl": "https://rr2---sn-8v5oxucg-nn5e.googlevideo.com/videoplayback?expire=1751273548&ei=zN9haLKNGdqIxtYP28TR8Aw&ip=200.106.211.8&id=21ffb90b2ccf8e89&itag=18&source=blogger&xpc=Egho7Zf3LnoBAQ%3D%3D&met=1751244748,&mh=tG&mm=31&mn=sn-8v5oxucg-nn5e&ms=au&mv=m&mvi=2&pl=24&rms=au,au&susc=bl&eaua=OfoyTv86HTM&mime=video/mp4&vprv=1&rqh=1&dur=1504.026&lmt=1663907781639262&mt=1751244554&txp=1311224&sparams=expire,ei,ip,id,itag,source,xpc,susc,eaua,mime,vprv,rqh,dur,lmt&sig=AJfQdSswRQIgXqnGws612MTzXoaAdBzXR_oLLJYi6-qA_tzdFx7SAiMCIQDzKynyrDyiyU36OvgcZZgesTkjEJ0yGnZeAi7MOQpvUQ%3D%3D&lsparams=met,mh,mm,mn,ms,mv,mvi,pl,rms&lsig=APaTxxMwRgIhALDHvSHHQKSV_y3HGpUPsfTJGG1fJudsF33VGAWNs0YBAiEA_urgD1MFv7n1jgJTIfD0_yPLEL36tzAPK2xa_jUsp7Y%3D&cpn=wbRPZdsjuUdzRBne&c=WEB_EMBEDDED_PLAYER&cver=1.20250624.21.00",
            "duration": 1503
          }
        ]
      }
    ],
    "year": 2021,
    "rating": 7.7,
    "openings": [],
    "endings": [],
    "osts": []
  },
  {
    "id": 10,
    "title": "Miss Kobayashi's Dragon Maid",
    "description": "Um funcionário de escritório contrata um dragão de coração bondoso para servir como sua empregada e entra em um mundo de desventuras cômicas.",
    "thumbnail": "https://raw.githubusercontent.com/jonarasgames/AniVerse/refs/heads/main/images/thumbnails/misskobayashianime.jpg",
    "trailer": "https://www.youtube.com/watch?v=4N6ozeZ2cA0",
    "type": "anime",
    "dateAdded": "2025-07-02",
    "categories": [
      "comedy",
      "adventure",
      "slice of life"
    ],
    "seasons": [
      {
        "number": 1,
        "episodes": [
          {
            "title": "Episódio 1",
            "videoUrl": "a",
            "duration": 0
          }
        ]
      }
    ],
    "year": 2017,
    "rating": 7.7,
    "openings": [
      {
        "title": "Blue Sky Rhapsody",
        "artist": "Fhána",
        "audio": "https://dn721806.ca.archive.org/0/items/misskobayashisdragonmaidopfull/Miss_kobayashis_dragon_maidOpFull.mp3",
        "cover": "https://static.wikia.nocookie.net/maid-dragon/images/d/de/108125_686683.jpg",
        "type": "opening",
        "season": 1
      },
      {
        "title": "Ai no Supreme!",
        "artist": "fhána",
        "audio": "https://jonaras.s-ul.eu/ds5lZYDG",
        "cover": "https://static.wikia.nocookie.net/maid-dragon/images/b/b8/Ai_No_Supreme_CD_Cover.jpg",
        "type": "opening",
        "season": 2
      }
    ],
    "endings": [
      {
        "title": "Ishukan Communication",
        "artist": "Choro-gonzu",
        "audio": "https://jonaras.s-ul.eu/AQyn08dm",
        "cover": "https://static.wikia.nocookie.net/maid-dragon/images/8/8c/Ishukan_Communication_Cover.jpg",
        "type": "ending",
        "season": 1
      },
      {
        "title": "Maid with Dragons ︎❤︎",
        "artist": "Super Chorogons",
        "audio": "https://jonaras.s-ul.eu/kvukHM8P",
        "cover": "https://static.wikia.nocookie.net/maid-dragon/images/0/00/Maid_with_Dragons_CD_Cover.jpg",
        "type": "ending",
        "season": 2
      }
    ],
    "osts": {}
  },
  {
    "id": 11,
    "title": "Azumanga Web Daioh",
    "description": "Chiyo leva uma câmera de vídeo para a escola para um projeto de classe. Mas quando Tomo a pega, uma série de problemas acontecem por toda a escola.",
    "thumbnail": "https://raw.githubusercontent.com/jonarasgames/AniVerse/refs/heads/main/images/thumbnails/azudaiohweb.png",
    "trailer": "nothing",
    "type": "ova",
    "dateAdded": "2025-07-07",
    "categories": [
      "comedy",
      "slice of life"
    ],
    "seasons": [
      {
        "number": 1,
        "episodes": [
          {
            "title": "Piloto",
            "videoUrl": "https://files.catbox.moe/9pp2h7.mp4",
            "duration": 223
          }
        ]
      }
    ],
    "year": 2000,
    "rating": 6.1,
    "openings": [],
    "endings": [],
    "osts": {}
  },
  {
    "id": 12,
    "title": "Azumanga Daioh: The Very Short Movie",
    "description": "Uma pequena compilação de esquetes humorísticos com um grupo de amigos do ensino médio.",
    "thumbnail": "https://raw.githubusercontent.com/jonarasgames/AniVerse/refs/heads/main/images/thumbnails/azudaiohova.png",
    "trailer": "num tem",
    "type": "ova",
    "dateAdded": "2025-07-08",
    "categories": [
      "comedy",
      "slice of life"
    ],
    "seasons": [
      {
        "number": 1,
        "episodes": [
          {
            "title": "Episódio 1",
            "videoUrl": "https://files.catbox.moe/puab95.mp4",
            "duration": 353
          }
        ]
      }
    ],
    "year": 2001,
    "rating": 7.3,
    "openings": [],
    "endings": [],
    "osts": {}
  },
  {
    "id": 13,
    "title": "Joshiraku",
    "description": "Marii, Kigurumi, Tetora, Gankyou e Kukuru merecem uma salva de palmas por manterem viva a arte do Rakugo! Qual é o segredo delas? Uma brincadeira espirituosa e absurda, é claro! Essas cinco amigas sempre têm assunto para conversar, não importa quão bobo seja ele.",
    "thumbnail": "https://raw.githubusercontent.com/jonarasgames/AniVerse/refs/heads/main/images/thumbnails/joshiraku.png",
    "trailer": "https://www.w3schools.com/html/mov_bbb.mp4",
    "type": "anime",
    "dateAdded": "2025-07-10",
    "categories": [
      "slice of life",
      "comedy"
    ],
    "seasons": [
      {
        "number": 1,
        "episodes": [
          {
            "title": "Diálogo Normal",
            "videoUrl": "https://files.catbox.moe/8rzp8h.mp4",
            "duration": 1466
          },
          {
            "title": "Bastidores Riquezas",
            "videoUrl": "https://files.catbox.moe/uj5462.mp4",
            "duration": 1448
          },
          {
            "title": "Um Banho Para Além",
            "videoUrl": "https://files.catbox.moe/553orz.mp4",
            "duration": 1448
          },
          {
            "title": "Garota Óculos",
            "videoUrl": "https://files.catbox.moe/romyv9.mp4",
            "duration": 1448
          },
          {
            "title": "Elogie A Menina",
            "videoUrl": "https://files.catbox.moe/wixj9n.mp4",
            "duration": 1450
          },
          {
            "title": "Quatro Emociona",
            "videoUrl": "https://files.catbox.moe/yv3gt2.mp4",
            "duration": 1450
          },
          {
            "title": "Yankees São Assustadores",
            "videoUrl": "https://files.catbox.moe/kfks7k.mp4",
            "duration": 1434
          },
          {
            "title": "Saco De Ouro",
            "videoUrl": "https://files.catbox.moe/jv1iwc.mp4",
            "duration": 1434
          },
          {
            "title": "Butttofu",
            "videoUrl": "https://files.catbox.moe/7n7aso.mp4",
            "duration": 1434
          },
          {
            "title": "Banda De Abóbora",
            "videoUrl": "https://files.catbox.moe/y23b90.mp4",
            "duration": 1434
          },
          {
            "title": "Jogo Família",
            "videoUrl": "https://files.catbox.moe/j00nuh.mp4",
            "duration": 1434
          },
          {
            "title": "O Sonhador Contra Ataca!",
            "videoUrl": "https://files.catbox.moe/bply33.mp4",
            "duration": 1434
          },
          {
            "title": "Coragem Do Personagem",
            "videoUrl": "https://files.catbox.moe/9yhua2.mp4",
            "duration": 1419
          }
        ]
      }
    ],
    "year": 2012,
    "rating": 7,
    "openings": [
      {
        "title": "Oato ga Yoroshikutte... yo!",
        "artist": "Gokuraku Jokai",
        "audio": "https://files.catbox.moe/ouerl4.mp3",
        "cover": "https://m.media-amazon.com/images/I/715ax108MTL._UF1000,1000_QL80_.jpg",
        "type": "opening",
        "season": 1
      }
    ],
    "endings": [
      {
        "title": "Nippon Egao Hyakkei",
        "artist": "Momokurotei Ichimon",
        "audio": "https://files.catbox.moe/pzb0yb.mp3",
        "cover": "https://i.scdn.co/image/ab67616d0000b273d4a4f25d06fa3717eb4b2193",
        "type": "ending",
        "season": 1
      }
    ],
    "osts": {}
  },
  {
    "id": 14,
    "title": "Joshiraku OVA",
    "description": "Episódio OVA incluído no quinto volume do mangá.",
    "thumbnail": "https://simkl.in/fanart/67/678476efef177c6c_w.jpg",
    "trailer": "assasina",
    "type": "ova",
    "dateAdded": "2025-07-10",
    "categories": [
      "comedy",
      "slice of life"
    ],
    "seasons": [
      {
        "number": 1,
        "episodes": [
          {
            "title": "Episódio 14",
            "videoUrl": "https://files.catbox.moe/rzewv2.mp4",
            "duration": 1420
          }
        ]
      }
    ],
    "year": 2013,
    "rating": 7.3,
    "openings": [],
    "endings": [],
    "osts": {}
  },
  {
    "id": 15,
    "title": "Dan Da Dan",
    "description": "Quando as crenças de Momo e Okarun entram em conflito, eles são jogados em um mundo de fantasmas, alienígenas e poderes despertos.",
    "thumbnail": "https://raw.githubusercontent.com/jonarasgames/AniVerse/refs/heads/main/images/thumbnails/dandadanime.png",
    "trailer": "https://www.youtube.com/embed/MGRm4IzK1SQ?autoplay=1&mute=1&enablejsapi=1",
    "type": "anime",
    "dateAdded": "2025-07-12",
    "categories": [
      "action",
      "comedy",
      "slice of life"
    ],
    "seasons": [
      {
        "number": 1,
        "episodes": [
          {
            "title": "É Assim Que um Amor Começa!",
            "videoUrl": "https://zggg98sgwbg1gh.bitchute.com/8xBkY2iNMQ05/86EFkNp06Q1s.mp4",
            "duration": 1479
          },
          {
            "title": "Isso Aí É um Alienígena, Né?!",
            "videoUrl": "https://files.catbox.moe/tbstae.mp4",
            "duration": 1477
          },
          {
            "title": "Uma Disputa de Velha contra Velha",
            "videoUrl": "https://files.catbox.moe/rtt8bk.mp4",
            "duration": 1483
          },
          {
            "title": "Hora de Arrebentar Com a Velha Turbo",
            "videoUrl": "https://seed132.bitchute.com/8xBkY2iNMQ05/01ojoyeEC9RT.mp4",
            "duration": 1483
          },
          {
            "title": "Cadê Tuas Bolas, Cara?",
            "videoUrl": "https://files.catbox.moe/veucsu.mp4",
            "duration": 1485
          },
          {
            "title": "Surge uma Mulher Perigosa",
            "videoUrl": "https://seed167.bitchute.com/8xBkY2iNMQ05/mg9pyIGEYUgb.mp4",
            "duration": 1483
          },
          {
            "title": "Rumo a um Mundo Gentil",
            "videoUrl": "https://seed132.bitchute.com/8xBkY2iNMQ05/6DRBdpGgJhHI.mp4",
            "duration": 1483
          },
          {
            "title": "Ela Tá Meio Bolada",
            "videoUrl": "https://files.catbox.moe/779gfr.mp4",
            "duration": 1470
          },
          {
            "title": "Fusão! Serpiano Demônio de Dover Nessie!",
            "videoUrl": "https://seed122.bitchute.com/8xBkY2iNMQ05/78yz8FGtp3WR.mp4",
            "duration": 1472
          },
          {
            "title": "Você Já Viu uma Abdução de Gado?",
            "videoUrl": "https://files.catbox.moe/ayu0q7.mp4",
            "duration": 1470
          },
          {
            "title": "O Primeiro Amor",
            "videoUrl": "https://files.catbox.moe/br7lxd.mp4",
            "duration": 1470
          },
          {
            "title": "Simbora Pra Casa Amaldiçoada!",
            "videoUrl": "https://files.catbox.moe/xsfqa8.mp4",
            "duration": 1455
          }
        ]
      },
      {
        "number": 2,
        "episodes": [
          {
            "title": "Então essa é a lendária cobra gigante?",
            "videoUrl": "https://zggg98sgwbg1gh.bitchute.com/8xBkY2iNMQ05/AbKx8aUh8yP1.mp4",
            "duration": 1499
          },
          {
            "title": "O Olho Demoníaco",
            "videoUrl": "https://zn21g5kls-n995.bitchute.com/8xBkY2iNMQ05/1tUfYdthvHjD.mp4",
            "duration": 1495
          },
          {
            "title": "Imperdoável",
            "videoUrl": "",
            "duration": 0
          }
        ]
      }
    ],
    "year": 2024,
    "rating": 8.3,
    "openings": [
      {
        "title": "Otonoke",
        "artist": "Creepy Nuts",
        "audio": "https://files.catbox.moe/s9x422.mp3",
        "cover": "https://static.wikia.nocookie.net/dandadan/images/0/07/Otonoke_Cover.png",
        "type": "opening",
        "season": 1
      },
      {
        "title": "On The Way",
        "artist": "AiNA THE END",
        "audio": "https://files.catbox.moe/9oojg2.mp3",
        "cover": "https://static.wikia.nocookie.net/dandadan/images/0/04/Ontheway.png",
        "type": "opening",
        "season": 2
      }
    ],
    "endings": [
      {
        "title": "TAIDADA",
        "artist": "ZUTOMAYO",
        "audio": "https://files.catbox.moe/cqtcsj.mp3",
        "cover": "https://static.wikia.nocookie.net/dandadan/images/4/4c/TAIDADA_Cover.png",
        "type": "ending",
        "season": 1
      },
      {
        "title": "Something's Wrong with Them",
        "artist": " WurtS",
        "audio": "https://files.catbox.moe/iuw9wk.mp3",
        "cover": "https://static.wikia.nocookie.net/dandadan/images/d/d4/Doukashiteru_Cover.png",
        "type": "ending",
        "season": 2
      }
    ],
    "osts": {}
  }
]
